libcli/__init__.py
libcli/getopt.py
libcli/opttools.py
libcli-0.3.3.dist-info/DESCRIPTION.rst
libcli-0.3.3.dist-info/METADATA
libcli-0.3.3.dist-info/RECORD
libcli-0.3.3.dist-info/WHEEL
libcli-0.3.3.dist-info/metadata.json
libcli-0.3.3.dist-info/top_level.txt
