Metadata-Version: 2.0
Name: libcli
Version: 0.3.3
Summary: Library helps to build command line interface
Home-page: https://github.com/stepheny/pylibcli
Author: Stephen.Y
Author-email: stephen.jin.yee@gmail.com
License: MIT
Platform: UNKNOWN
Classifier: Development Status :: 3 - Alpha
Classifier: Environment :: Console
Classifier: Intended Audience :: Developers
Classifier: License :: OSI Approved :: MIT License
Classifier: Natural Language :: English
Classifier: Operating System :: POSIX :: Linux
Classifier: Programming Language :: Python :: 3
Classifier: Topic :: Software Development :: Libraries :: Python Modules
